uniteampckg/__init__.py
uniteampckg/constants/__init__.py
uniteampckg/constants/error_constant.py
uniteampckg/db/__init__.py
uniteampckg/db/db_util.py
uniteampckg/db/migrations/v_2_0.sql
uniteampckg/db/model/__init__.py
uniteampckg/db/model/back_admin_tables.py
uniteampckg/db/model/call_tables.py
uniteampckg/db/model/company_tables.py
uniteampckg/db/model/config_tables.py
uniteampckg/db/model/connect_tables.py
uniteampckg/db/model/contest_tables.py
uniteampckg/db/model/db_base_model.py
uniteampckg/db/model/distribute_tables.py
uniteampckg/db/model/feed_tables.py
uniteampckg/db/model/general_tables.py
uniteampckg/db/model/notification_tables.py
uniteampckg/db/model/occasion_tables.py
uniteampckg/db/model/poll_tables.py
uniteampckg/db/model/purchase_tables.py
uniteampckg/db/model/recognition_tables.py
uniteampckg/db/model/session_tables.py
uniteampckg/db/model/shop_tables.py
uniteampckg/db/model/survey_tables.py
uniteampckg/db/model/user_tables.py
uniteampckg/models/__init__.py
uniteampckg/models/base_models.py
uniteampckg/models/route_models.py
uniteampckg/utils/__init__.py
uniteampckg/utils/decorators/__init__.py
uniteampckg/utils/decorators/common_decorator.py
uniteampckg/utils/logging/__init__.py
uniteampckg/utils/logging/logger.py
uniteam_backend_package-0.1.2335.dist-info/METADATA
uniteam_backend_package-0.1.2335.dist-info/WHEEL
uniteam_backend_package-0.1.2335.dist-info/RECORD
